TelegramSDK/TelegramSDK.py
TelegramSDK/__init__.py
TelegramSDK/telegram.py
TelegramSDK/util.py
TelSDK-0.1.2.dist-info/METADATA
TelSDK-0.1.2.dist-info/WHEEL
TelSDK-0.1.2.dist-info/top_level.txt
TelSDK-0.1.2.dist-info/RECORD
