Metadata-Version: 2.1
Name: TelSDK
Version: 0.1.2
Summary: Simple Telegram bot library
Home-page: https://github.com/cirebon-dev/TelegramSDK
Author: guangrei
Author-email: myawn@pm.me
License: MIT
Platform: any
Requires-Dist: requests
Requires-Dist: zcache
